ethereum_wallet_mcp/__init__.py
ethereum_wallet_mcp/server.py
ethereum_wallet_mcp/prompts/__init__.py
ethereum_wallet_mcp/prompts/signing_prompts.py
ethereum_wallet_mcp/prompts/wallet_prompts.py
ethereum_wallet_mcp/resources/__init__.py
ethereum_wallet_mcp/resources/documentation.py
ethereum_wallet_mcp/resources/signing_resources.py
ethereum_wallet_mcp/tools/__init__.py
ethereum_wallet_mcp/tools/signing.py
ethereum_wallet_mcp/tools/typed_data.py
ethereum_wallet_mcp/tools/wallet_generation.py
ethereum_wallet_mcp-1.0.0.dist-info/METADATA
ethereum_wallet_mcp-1.0.0.dist-info/WHEEL
ethereum_wallet_mcp-1.0.0.dist-info/entry_points.txt
ethereum_wallet_mcp-1.0.0.dist-info/RECORD
